syntactic_cache/__init__.py
syntactic_cache/decorators.py
syntactic_cache-1.1.0.dist-info/licenses/LICENCE
syntactic_cache-1.1.0.dist-info/METADATA
syntactic_cache-1.1.0.dist-info/WHEEL
syntactic_cache-1.1.0.dist-info/top_level.txt
syntactic_cache-1.1.0.dist-info/RECORD
