Metadata-Version: 2.4
Name: syntactic-cache
Version: 1.1.0
Summary: Syntactic cached property generator for classes.
Author-email: Leo Turnell-Ritson <l.turnell.ritson@gmail.com>
License: MIT
Project-URL: Repository, https://github.com/LeoTurnell-Ritson/syntactic-cache
Requires-Python: >=3
License-File: LICENCE
Provides-Extra: dev
Requires-Dist: ruff; extra == "dev"
Provides-Extra: test
Requires-Dist: coverage; extra == "test"
Dynamic: license-file
